xyscreens/__init__.py
xyscreens/__main__.py
xyscreens/_version.py
xyscreens/py.typed
xyscreens/xyscreens.py
xyscreens-1.0.0.dist-info/METADATA
xyscreens-1.0.0.dist-info/WHEEL
xyscreens-1.0.0.dist-info/licenses/LICENSE
xyscreens-1.0.0.dist-info/RECORD
